conexion_a_db/__init__.py
conexion_a_db/conexion_a_db.py
conexion_a_db-0.0.5.dist-info/METADATA
conexion_a_db-0.0.5.dist-info/WHEEL
conexion_a_db-0.0.5.dist-info/top_level.txt
conexion_a_db-0.0.5.dist-info/RECORD
