Metadata-Version: 2.4
Name: conexion_a_db
Version: 0.0.5
Summary: Librería para conectarse a bases de datos fácilmente.
Home-page: https://github.com/tu_usuario/conexion_a_db
Author: Gerardo Rios Navarrete
Author-email: gerardoriosn@gmail.com
Classifier: Programming Language :: Python :: 3
Dynamic: author
Dynamic: author-email
Dynamic: classifier
Dynamic: description-content-type
Dynamic: home-page
Dynamic: summary
